pymetasploit3/__init__.py
pymetasploit3/msfconsole.py
pymetasploit3/msfrpc.py
pymetasploit3/utils.py
pymetasploit3-1.0.4.data/scripts/pymsfconsole.py
pymetasploit3-1.0.4.data/scripts/pymsfrpc.py
pymetasploit3-1.0.4.dist-info/LICENSE
pymetasploit3-1.0.4.dist-info/METADATA
pymetasploit3-1.0.4.dist-info/WHEEL
pymetasploit3-1.0.4.dist-info/top_level.txt
pymetasploit3-1.0.4.dist-info/RECORD
