Metadata-Version: 2.1
Name: pymetasploit3
Version: 1.0.4
Summary: A full-fledged msfrpc library for Metasploit framework.
Home-page: https://github.com/DanMcInerney/pymetasploit3
Author: Dan McInerney
Author-email: danhmcinerney@gmail.com
License: GPL
Download-URL: https://github.com/DanMcInerney/pymetasploit3/zipball/master
Platform: UNKNOWN
License-File: LICENSE
Requires-Dist: msgpack
Requires-Dist: requests
Requires-Dist: retry
